[
   {
      "id": "c296567d-dadf-5f9e-818d-e46f304cad24",
      "name": "比良坂 夜露",
      "shortName": "比良坂 夜露",
      "attribute": "electric",
      "imagePath": "yotuyu_n"
   },
   {
      "id": "524fbde2-634a-51fd-af73-bdd1bffc7abd",
      "name": "比良坂 夜露",
      "shortName": "比良坂 夜露",
      "another": "勇躍",
      "attribute": "electric",
      "imagePath": "yotuyu_a"
   },
   {
      "id": "30b8fc57-bfb1-45e8-b0de-44a9c56b683f",
      "name": "比良坂 夜露",
      "shortName": "比良坂 夜露",
      "factor": "コネクト",
      "attribute": "electric",
      "imagePath": "yotuyu_f"
   },
   {
      "id": "64d1dd5e-a7f5-57fa-9eae-0b49f428d3bd",
      "name": "兼志谷 シタラ",
      "shortName": "兼志谷 シタラ",
      "attribute": "gravity",
      "imagePath": "sitara_n"
   },
   {
      "id": "fd2779fc-6e4c-54e4-85c0-ddf4353874a6",
      "name": "兼志谷 シタラ",
      "shortName": "兼志谷 シタラ",
      "another": "天機",
      "attribute": "gravity",
      "imagePath": "sitara_a"
   },
   {
      "id": "a9d40413-6d9d-438c-b1f6-644c5f559b05",
      "name": "兼志谷 シタラ",
      "shortName": "兼志谷 シタラ",
      "factor": "ブレイブ",
      "attribute": "gravity",
      "imagePath": "sitara_f"
   },
   {
      "id": "8bed052f-fa26-5cf7-914e-64483f5f6862",
      "name": "百科 文嘉",
      "shortName": "百科 文嘉",
      "attribute": "freeze",
      "imagePath": "fumika_n"
   },
   {
      "id": "df1534c0-f647-5440-afc2-c06b7b144329",
      "name": "百科 文嘉",
      "shortName": "百科 文嘉",
      "another": "智将",
      "attribute": "freeze",
      "imagePath": "fumika_a"
   },
   {
      "id": "4d7d4432-59c8-42e4-8dda-83a72cafd839",
      "name": "百科 文嘉",
      "shortName": "百科 文嘉",
      "factor": "ブレイブ",
      "attribute": "freeze",
      "imagePath": "fumika_f"
   },
   {
      "id": "80705fb4-7c64-5675-828c-856485053260",
      "name": "吾妻 楓",
      "shortName": "吾妻 楓",
      "attribute": "electric",
      "imagePath": "kaede_n"
   },
   {
      "id": "b67644c1-e5d9-5b28-b643-c2d6537114fe",
      "name": "吾妻 楓",
      "shortName": "吾妻 楓",
      "another": "皆伝",
      "attribute": "electric",
      "imagePath": "kaede_a"
   },
   {
      "id": "e085acd5-416e-40a0-b655-2e001b91e1ba",
      "name": "吾妻 楓",
      "shortName": "吾妻 楓",
      "factor": "ネクスト",
      "attribute": "electric",
      "imagePath": "kaede_f"
   },
   {
      "id": "90be9da8-126e-52d6-9194-0954eab0fe63",
      "name": "日向 リン",
      "shortName": "日向 リン",
      "attribute": "heat",
      "imagePath": "rin_n"
   },
   {
      "id": "cc5a0920-6242-55bf-8254-b6445fa7530a",
      "name": "日向 リン",
      "shortName": "日向 リン",
      "another": "奔放",
      "attribute": "heat",
      "imagePath": "rin_a"
   },
   {
      "id": "5f6d468e-38ed-4b5c-813c-3cbad747c28f",
      "name": "日向 リン",
      "shortName": "日向 リン",
      "factor": "ネクスト",
      "attribute": "heat",
      "imagePath": "rin_f"
   },
   {
      "id": "02bbdd80-0124-5ef7-93b1-cf81eac80362",
      "name": "小鳥遊 怜",
      "shortName": "小鳥遊 怜",
      "attribute": "freeze",
      "imagePath": "rei_n"
   },
   {
      "id": "e33989c6-8970-5936-8277-ec39c3c40168",
      "name": "小鳥遊 怜",
      "shortName": "小鳥遊 怜",
      "another": "蒼穹",
      "attribute": "freeze",
      "imagePath": "rei_a"
   },
   {
      "id": "198ee13d-b8f3-4f90-a610-97e47abea7bb",
      "name": "小鳥遊 怜",
      "shortName": "小鳥遊 怜",
      "factor": "ネクスト",
      "attribute": "freeze",
      "imagePath": "rei_f"
   },
   {
      "id": "2be48d40-2e9f-5d41-96af-cacda61be3d6",
      "name": "一条 綾香",
      "shortName": "一条 綾香",
      "attribute": "heat",
      "imagePath": "ayaka_n"
   },
   {
      "id": "a99edaac-193d-5b3d-9af8-49d7f70044af",
      "name": "一条 綾香",
      "shortName": "一条 綾香",
      "another": "英俊",
      "attribute": "heat",
      "imagePath": "ayaka_a"
   },
   {
      "id": "099484f6-2668-4d03-a98f-af24bca0242f",
      "name": "一条 綾香",
      "shortName": "一条 綾香",
      "factor": "ネクスト",
      "attribute": "heat",
      "imagePath": "ayaka_f"
   },
   {
      "id": "0ac797a3-378b-568f-b07d-28bee2f0eb21",
      "name": "相河 愛花",
      "shortName": "相河 愛花",
      "attribute": "electric",
      "imagePath": "aika_n"
   },
   {
      "id": "45c59373-5d83-55ad-928d-52286b84af70",
      "name": "相河 愛花",
      "shortName": "相河 愛花",
      "another": "仁愛",
      "attribute": "electric",
      "imagePath": "aika_a"
   },
   {
      "id": "87ea6f43-1b63-40a0-b993-c825490937e1",
      "name": "相河 愛花",
      "shortName": "相河 愛花",
      "factor": "ネクスト",
      "attribute": "electric",
      "imagePath": "aika_f"
   },
   {
      "id": "7d189302-1f2f-5c8b-8c9a-2ce0537461d5",
      "name": "小芦 睦海",
      "shortName": "小芦 睦海",
      "attribute": "freeze",
      "imagePath": "mutumi_n"
   },
   {
      "id": "be2827cd-ff12-5236-935b-815af41f3a8d",
      "name": "小芦 睦海",
      "shortName": "小芦 睦海",
      "another": "剛毅",
      "attribute": "freeze",
      "imagePath": "mutumi_a"
   },
   {
      "id": "0973a3b4-f57b-44a9-9d4c-f27852c95311",
      "name": "小芦 睦海",
      "shortName": "小芦 睦海",
      "factor": "ネクスト",
      "attribute": "freeze",
      "imagePath": "mutumi_f"
   },
   {
      "id": "bf3cb9cc-d453-5b0b-9b6d-2ebfe328a60b",
      "name": "二子玉 舞",
      "shortName": "二子玉 舞",
      "attribute": "freeze",
      "imagePath": "mai_n"
   },
   {
      "id": "9eb57a94-32a8-5ed0-981e-470d0945a42b",
      "name": "二子玉 舞",
      "shortName": "二子玉 舞",
      "another": "繊麗",
      "attribute": "freeze",
      "imagePath": "mai_a"
   },
   {
      "id": "bfd31285-1044-4318-bf59-71e7ca923381",
      "name": "二子玉 舞",
      "shortName": "二子玉 舞",
      "factor": "ライブ",
      "attribute": "freeze",
      "imagePath": "mai_f"
   },
   {
      "id": "a83c8598-dfac-502b-b43f-587552df34ca",
      "name": "バージニア・グリンベレー",
      "shortName": "バージニア・G",
      "attribute": "heat",
      "imagePath": "virginia_n"
   },
   {
      "id": "11f3664e-08e2-52a6-96ff-413ab71bc59b",
      "name": "バージニア・グリンベレー",
      "shortName": "バージニア・G",
      "another": "MOBIUS",
      "attribute": "heat",
      "imagePath": "virginia_a"
   },
   {
      "id": "d1d5ef95-f427-4f08-b6d3-4fce54469028",
      "name": "バージニア・グリンベレー",
      "shortName": "バージニア・G",
      "factor": "ライブ",
      "attribute": "heat",
      "imagePath": "virginia_f"
   },
   {
      "id": "51b87bbf-d0f5-55f1-84d3-a18d8e649b50",
      "name": "ファティマ・ベトロラム",
      "shortName": "ファティマ・B",
      "attribute": "heat",
      "imagePath": "fatima_n"
   },
   {
      "id": "692e6020-7d04-4f41-825c-27425e6ed4a3",
      "name": "ファティマ・ベトロラム",
      "shortName": "ファティマ・B",
      "attribute": "heat",
      "another": "Miθra",
      "imagePath": "fatima_a"
   },
   {
      "id": "0fe1fe78-00a3-5fb3-ba7c-385da4329faa",
      "name": "四谷 ゆみ",
      "shortName": "四谷 ゆみ",
      "attribute": "gravity",
      "imagePath": "yumi_n"
   },
   {
      "id": "7ba34cc4-076d-577c-8765-66946bec9d4e",
      "name": "四谷 ゆみ",
      "shortName": "四谷 ゆみ",
      "another": "絢爛",
      "attribute": "gravity",
      "imagePath": "yumi_a"
   },
   {
      "id": "c3a7d771-bfca-5528-8763-4b60ee408362",
      "name": "藤野 やよい",
      "shortName": "藤野 やよい",
      "attribute": "heat",
      "imagePath": "yayoi_n"
   },
   {
      "id": "ab333ca8-32f7-5c8e-9410-7c670c5d4796",
      "name": "藤野 やよい",
      "shortName": "藤野 やよい",
      "another": "無常",
      "attribute": "heat",
      "imagePath": "yayoi_a"
   },
   {
      "id": "b33233fc-399e-4f41-bcf3-96f49bd27cbe",
      "name": "藤野 やよい",
      "shortName": "藤野 やよい",
      "factor": "ライブ",
      "attribute": "heat",
      "imagePath": "yayoi_f"
   },
   {
      "id": "4fda603f-613c-5a6d-814e-72668eb4e6ab",
      "name": "下落合 桃歌",
      "shortName": "下落合 桃歌",
      "attribute": "electric",
      "imagePath": "touka_n"
   },
   {
      "id": "09a1fc35-5efc-5212-b0c2-9568ed6539c5",
      "name": "下落合 桃歌",
      "shortName": "下落合 桃歌",
      "another": "明星",
      "attribute": "electric",
      "imagePath": "touka_a"
   },
   {
      "id": "d5baa787-a5cd-4165-b3cd-513bdbf38c9a",
      "name": "下落合 桃歌",
      "shortName": "下落合 桃歌",
      "factor": "ライブ",
      "attribute": "electric",
      "imagePath": "touka_f"
   },
   {
      "id": "6c3d36fe-1fc6-5362-9d1a-45060c6c37a8",
      "name": "シャーリー・オークレイ",
      "shortName": "シャーリー・O",
      "attribute": "electric",
      "imagePath": "shirley_n"
   },
   {
      "id": "b9635a59-472f-4975-ac5a-b868d75798c2",
      "name": "シャーリー・オークレイ",
      "shortName": "シャーリー・O",
      "attribute": "electric",
      "another": "撃壌",
      "imagePath": "shirley_a"
   },
   {
      "id": "c219fd59-eba2-4540-a5b0-48fa49cfa30e",
      "name": "伊戸倉 音緒",
      "shortName": "伊戸倉 音緒",
      "attribute": "electric",
      "imagePath": "neo_n"
   },
   {
      "id": "f919e8be-6cda-4eed-9698-130c93c321f4",
      "name": "伊戸倉 音緒",
      "shortName": "伊戸倉 音緒",
      "attribute": "electric",
      "another": "破手",
      "imagePath": "neo_a"
   },
   {
      "id": "2351eb07-c832-5b2d-b40c-759adcc65911",
      "name": "依城 えり",
      "shortName": "依城 えり",
      "attribute": "freeze",
      "imagePath": "eri_n"
   },
   {
      "id": "7532bc8d-2eb3-5d28-9b85-e263a4727778",
      "name": "依城 えり",
      "shortName": "依城 えり",
      "another": "清廉",
      "attribute": "freeze",
      "imagePath": "eri_a"
   },
   {
      "id": "cd00dee0-a890-58f8-889c-ac27146f2cb3",
      "name": "文島 明日翔",
      "shortName": "文島 明日翔",
      "attribute": "heat",
      "imagePath": "asuka_n"
   },
   {
      "id": "ba2682ee-c0e9-491f-9879-89099fd4638a",
      "name": "文島 明日翔",
      "shortName": "文島 明日翔",
      "attribute": "heat",
      "another": "福音",
      "imagePath": "asuka_a"
   },
   {
      "id": "2a9043cb-e219-53a5-84a9-141631192fee",
      "name": "大関 小結",
      "shortName": "大関 小結",
      "attribute": "gravity",
      "imagePath": "koyui_n"
   },
   {
      "id": "ec0f131c-beac-5402-a0b1-94bc15628d76",
      "name": "大関 小結",
      "shortName": "大関 小結",
      "another": "豊潤",
      "attribute": "gravity",
      "imagePath": "koyui_a"
   },
   {
      "id": "2266bbec-6847-574b-bc2a-652805eb75af",
      "name": "宇佐元 杏奈",
      "shortName": "宇佐元 杏奈",
      "attribute": "electric",
      "imagePath": "anna_n"
   },
   {
      "id": "c450acd0-0932-5152-bdda-b4a0024f7de8",
      "name": "宇佐元 杏奈",
      "shortName": "宇佐元 杏奈",
      "another": "希求",
      "attribute": "electric",
      "imagePath": "anna_a"
   },
   {
      "id": "053ec7dd-7a5b-4392-b6a0-b0c224a3b386",
      "name": "宇佐元 杏奈",
      "shortName": "宇佐元 杏奈",
      "factor": "レジェンド",
      "attribute": "electric",
      "imagePath": "anna_f"
   },
   {
      "id": "e271e041-4468-5be2-82cf-853e212c42a3",
      "name": "神宮寺 真理",
      "shortName": "神宮寺 真理",
      "attribute": "electric",
      "imagePath": "mari_n"
   },
   {
      "id": "c93044f7-f5a3-5222-b8f8-6fa8ee74e6db",
      "name": "神宮寺 真理",
      "shortName": "神宮寺 真理",
      "another": "孤影",
      "attribute": "electric",
      "imagePath": "mari_a"
   },
   {
      "id": "0706ed5b-94bf-4eed-9dfb-4903a48ccea3",
      "name": "神宮寺 真理",
      "shortName": "神宮寺 真理",
      "factor": "レジェンド",
      "attribute": "electric",
      "imagePath": "mari_f"
   },
   {
      "id": "dda4a5a7-b6ed-5341-9bec-c18f996d2476",
      "name": "新谷 芹菜",
      "shortName": "新谷 芹菜",
      "attribute": "gravity",
      "imagePath": "serina_n"
   },
   {
      "id": "02d9db64-8177-4461-8380-88687234ad5d",
      "name": "新谷 芹菜",
      "shortName": "新谷 芹菜",
      "attribute": "gravity",
      "another": "燐光",
      "imagePath": "serina_a"
   },
   {
      "id": "67d8d959-8b1c-5784-be11-45768e0ddc69",
      "name": "蛙坂 来弥",
      "shortName": "蛙坂 来弥",
      "attribute": "heat",
      "imagePath": "raiya_n"
   },
   {
      "id": "0e3b31c6-b897-579b-84c4-0f987599c992",
      "name": "蛙坂 来弥",
      "shortName": "蛙坂 来弥",
      "another": "残火",
      "attribute": "heat",
      "imagePath": "raiya_a"
   },
   {
      "id": "7a75ca0f-f410-46d3-820e-8a5b67d883eb",
      "name": "蛙坂 来弥",
      "shortName": "蛙坂 来弥",
      "factor": "ネクスト",
      "attribute": "heat",
      "imagePath": "raiya_f"
   },
   {
      "id": "b4a7adf7-0f5d-55ce-844c-80f3bed7ba24",
      "name": "籠目 深沙希",
      "shortName": "籠目 深沙希",
      "attribute": "gravity",
      "imagePath": "misaki_n"
   },
   {
      "id": "821e524c-be99-49c8-92ca-722679dc4eee",
      "name": "籠目 深沙希",
      "shortName": "籠目 深沙希",
      "attribute": "gravity",
      "another": "泡影",
      "imagePath": "misaki_a"
   },
   {
      "id": "de2ffde7-bd7d-54d5-adf9-cb055f1cfd4e",
      "name": "紺堂 地衛理",
      "shortName": "紺堂 地衛理",
      "attribute": "freeze",
      "imagePath": "chieri_n"
   },
   {
      "id": "7d7e74d4-b7e6-4bd6-9618-73774a23fb4f",
      "name": "紺堂 地衛理",
      "shortName": "紺堂 地衛理",
      "attribute": "freeze",
      "imagePath": "chieri_a",
      "another": "晨星"
   },
   {
      "id": "8b0c216c-f575-59ca-9fc4-2d2eef2588bc",
      "name": "州天頃 椎奈",
      "shortName": "州天頃 椎奈",
      "attribute": "electric",
      "imagePath": "siina_n"
   },
   {
      "id": "703f5667-13b3-4e80-bd92-00ff2b19be70",
      "name": "州天頃 椎奈",
      "shortName": "州天頃 椎奈",
      "attribute": "electric",
      "imagePath": "siina_a",
      "another": "玉響"
   },
   {
      "id": "340b00f6-db51-4341-9eba-59acbdafa7b9",
      "name": "州天頃 椎奈",
      "shortName": "州天頃 椎奈",
      "attribute": "electric",
      "imagePath": "siina_f",
      "factor": "ブレイブ"
   },
   {
      "id": "72647534-fe4e-50ac-8f0c-4217b209e225",
      "name": "仁紀藤 奏",
      "shortName": "仁紀藤 奏",
      "attribute": "gravity",
      "imagePath": "kanade_n"
   },
   {
      "id": "888cfb46-ca45-48a5-ab6d-ac7d0ac45894",
      "name": "仁紀藤 奏",
      "shortName": "仁紀藤 奏",
      "attribute": "gravity",
      "another": "雲耀",
      "imagePath": "kanade_a"
   },
   {
      "id": "3cce0a98-5a1c-4125-8d0b-a23101ba3591",
      "name": "仁紀藤 奏",
      "shortName": "仁紀藤 奏",
      "attribute": "gravity",
      "factor": "ブレイブ",
      "imagePath": "kanade_f"
   },
   {
      "id": "abc1c22b-8681-51c3-a7f3-3141d38a561e",
      "name": "村尾 未羅",
      "shortName": "村尾 未羅",
      "attribute": "gravity",
      "imagePath": "mira_n"
   },
   {
      "id": "f5d0ee22-7e3e-4483-94c6-7c4ccc45432b",
      "name": "村尾 未羅",
      "shortName": "村尾 未羅",
      "attribute": "gravity",
      "another": "至純",
      "imagePath": "mira_a"
   },
   {
      "id": "078cd8e5-bda0-5454-8195-b135d4a8cab9",
      "name": "君影 唯",
      "shortName": "君影 唯",
      "attribute": "electric",
      "imagePath": "yui_n"
   },
   {
      "id": "06c04449-8b81-4cd4-bbc7-37fb096ba491",
      "name": "君影 唯",
      "shortName": "君影 唯",
      "another": "連理",
      "attribute": "electric",
      "imagePath": "yui_a"
   },
   {
      "id": "ed1fe5bc-564e-5fde-b5a6-a3301488a5ca",
      "name": "須賀 乙莉",
      "shortName": "須賀 乙莉",
      "attribute": "gravity",
      "imagePath": "ituri_n"
   },
   {
      "id": "51b8b1d0-3467-41e4-b85c-5e3d7e285723",
      "name": "須賀 乙莉",
      "shortName": "須賀 乙莉",
      "attribute": "gravity",
      "another": "仰望",
      "imagePath": "ituri_a"
   },
   {
      "id": "73028a39-59b8-5f93-a703-6e07e5a56d26",
      "name": "萬場 盟華",
      "shortName": "萬場 盟華",
      "attribute": "heat",
      "imagePath": "meika_n"
   },
   {
      "id": "0bc0f145-f3c7-5ab4-a40a-5963fc3ee13f",
      "name": "萬場 盟華",
      "shortName": "萬場 盟華",
      "another": "極彩",
      "attribute": "heat",
      "imagePath": "meika_a"
   },
   {
      "id": "2a9f218e-e6a6-402b-a111-537ae0416972",
      "name": "九炉鉄 悠都",
      "shortName": "九炉鉄 悠都",
      "attribute": "heat",
      "imagePath": "yuuto_n"
   },
   {
      "id": "5d6f4053-2322-4b21-b232-354cc71e35a6",
      "name": "九炉鉄 悠都",
      "shortName": "九炉鉄 悠都",
      "attribute": "heat",
      "another": "引導",
      "imagePath": "yuuto_a"
   },
   {
      "id": "44003d42-471b-5c81-8861-6363b3e5c6d9",
      "name": "琴村 朱音",
      "shortName": "琴村 朱音",
      "attribute": "heat",
      "imagePath": "akane_n"
   },
   {
      "id": "b012983e-e494-4980-bc5f-d783c3c35e77",
      "name": "琴村 朱音",
      "shortName": "琴村 朱音",
      "attribute": "heat",
      "another": "炎天",
      "imagePath": "akane_a"
   },
   {
      "id": "25304260-abac-4e1f-a91a-5bd3ffc50c4f",
      "name": "琴村 朱音",
      "shortName": "琴村 朱音",
      "attribute": "heat",
      "factor": "ライブ",
      "imagePath": "akane_f"
   },
   {
      "id": "a8d41314-441b-5200-818c-390de5ce97c4",
      "name": "琴村 天音",
      "shortName": "琴村 天音",
      "attribute": "freeze",
      "imagePath": "amane_n"
   },
   {
      "id": "8c0de63c-e02e-4813-bb18-ae938fb2b2d5",
      "name": "琴村 天音",
      "shortName": "琴村 天音",
      "attribute": "freeze",
      "another": "玄天",
      "imagePath": "amane_a"
   },
   {
      "id": "3e518ca9-291c-4577-8962-998569223237",
      "name": "琴村 天音",
      "shortName": "琴村 天音",
      "attribute": "freeze",
      "factor": "ライブ",
      "imagePath": "amane_f"
   },
   {
      "id": "bc75747e-3ee5-5c54-86ce-00e5a66cfe6f",
      "name": "サンティ・ラナ",
      "shortName": "サンティ・R",
      "attribute": "gravity",
      "imagePath": "shanti_n"
   },
   {
      "id": "71d79c08-f999-4bed-b607-d4ef8274876b",
      "name": "サンティ・ラナ",
      "shortName": "サンティ・R",
      "another": "雄渾",
      "attribute": "gravity",
      "imagePath": "shanti_a"
   },
   {
      "id": "9203cbf4-3fe9-5465-a52a-c905084b7f9e",
      "name": "ニーナ・カリーニナ",
      "shortName": "ニーナ・K",
      "attribute": "freeze",
      "imagePath": "nina_n"
   },
   {
      "id": "34f4418a-099b-4202-9928-490893a1d694",
      "name": "ニーナ・カリーニナ",
      "shortName": "ニーナ・K",
      "attribute": "freeze",
      "another": "破軍",
      "imagePath": "nina_a"
   },
   {
      "id": "e67cf060-67a5-5d34-aa68-1f0ed5ceb351",
      "name": "王 紅花",
      "shortName": "王 紅花",
      "attribute": "heat",
      "imagePath": "honfa_n"
   },
   {
      "id": "480ce8d1-d213-5de5-8ba9-83c1303170d0",
      "name": "王 紅花",
      "shortName": "王 紅花",
      "another": "紅蓮",
      "attribute": "heat",
      "imagePath": "honfa_a"
   },
   {
      "id": "d51bbbc8-2dab-4027-902f-bbc849e65e99",
      "name": "ミア・ヴォワザン",
      "shortName": "ミア・V",
      "attribute": "freeze",
      "imagePath": "mia_n"
   },
   {
      "id": "2b63e550-a138-49d5-98f1-929f7757bdf2",
      "name": "ミア・ヴォワザン",
      "shortName": "ミア・V",
      "attribute": "freeze",
      "another": "恭敬",
      "imagePath": "mia_a"
   },
   {
      "id": "bb380504-396a-534c-bf61-2544a60caa10",
      "name": "千島 美幸",
      "shortName": "千島 美幸",
      "attribute": "electric",
      "imagePath": "miyuki_n"
   },
   {
      "id": "a2195eb3-6c1a-4e07-8ef9-0e7d3d46eca0",
      "name": "千島 美幸",
      "shortName": "千島 美幸",
      "attribute": "electric",
      "another": "幸魂",
      "imagePath": "miyuki_a"
   },
   {
      "id": "0984b942-a7e5-55fe-9827-328606ac25ad",
      "name": "東雲 チヱ",
      "shortName": "東雲 チヱ",
      "attribute": "heat",
      "imagePath": "tie_n"
   },
   {
      "id": "deb26f8a-b052-4796-aa57-b17041f7c03a",
      "name": "東雲 チヱ",
      "shortName": "東雲 チヱ",
      "attribute": "heat",
      "another": "流転",
      "imagePath": "tie_a"
   },
   {
      "id": "69c1fc91-7f13-51cf-874d-caf45031a6b8",
      "name": "御蔵座 梓希",
      "shortName": "御蔵座 梓希",
      "attribute": "electric",
      "imagePath": "azuki_n"
   },
   {
      "id": "15585b6e-93e6-46c1-a316-d20d9d309eb1",
      "name": "御蔵座 梓希",
      "shortName": "御蔵座 梓希",
      "attribute": "electric",
      "another": "招福",
      "imagePath": "azuki_a"
   },
   {
      "id": "13cf6980-87e7-5bfe-81d6-0cb9249f6a14",
      "name": "山野 薫子",
      "shortName": "山野 薫子",
      "attribute": "gravity",
      "imagePath": "kaoruko_n"
   },
   {
      "id": "3818b988-8437-42e1-897e-3ad53bbb77b7",
      "name": "山野 薫子",
      "shortName": "山野 薫子",
      "another": "玄妙",
      "attribute": "gravity",
      "imagePath": "kaoruko_a"
   },
   {
      "id": "b843d68b-2da2-5dd5-a7f5-cd21c76d584a",
      "name": "二階堂 司",
      "shortName": "二階堂 司",
      "attribute": "freeze",
      "imagePath": "tukasa_n"
   },
   {
      "id": "6312483f-f324-404b-b3e1-838ab18e3940",
      "name": "二階堂 司",
      "shortName": "二階堂 司",
      "attribute": "freeze",
      "another": "芝蘭",
      "imagePath": "tukasa_a"
   },
   {
      "id": "f28be965-4789-588c-92e4-e090a39619a3",
      "name": "御茶ノ水 美里江",
      "shortName": "御茶ノ水 美里江",
      "attribute": "electric",
      "imagePath": "mirie_n"
   },
   {
      "id": "f1b72249-4dd7-4393-b399-5ae76409d003",
      "name": "御茶ノ水 美里江",
      "shortName": "御茶ノ水 美里江",
      "another": "無辜",
      "attribute": "electric",
      "imagePath": "mirie_a"
   },
   {
      "id": "2e702ac8-7913-4c79-b7da-30404886c8ca",
      "name": "米良渕 花浪",
      "shortName": "米良渕 花浪",
      "attribute": "heat",
      "imagePath": "kanami_n"
   },
   {
      "id": "57bbebd8-3bf1-4c18-8c2c-054ff077ccf5",
      "name": "米良渕 花浪",
      "shortName": "米良渕 花浪",
      "attribute": "heat",
      "another": "大雅",
      "imagePath": "kanami_a"
   },
   {
      "id": "fd262118-4468-4a31-9524-40b776181f8c",
      "name": "駒添 絵伝",
      "shortName": "駒添 絵伝",
      "attribute": "heat",
      "imagePath": "eden_n"
   },
   {
      "id": "93735093-77a7-5fa6-849a-5d0226725208",
      "name": "リタ・ヘンシェル",
      "shortName": "リタ・H",
      "attribute": "gravity",
      "imagePath": "rita_n"
   },
   {
      "id": "6a8fa9fe-351f-4821-b681-550d24649d66",
      "name": "リタ・ヘンシェル",
      "shortName": "リタ・H",
      "another": "巧匠",
      "attribute": "gravity",
      "imagePath": "rita_a"
   },
   {
      "id": "c33aab32-f2c7-43f0-9281-54794b57a815",
      "name": "尾長 晶乃",
      "shortName": "尾長 晶乃",
      "attribute": "electric",
      "imagePath": "akino_n"
   },
   {
      "id": "46f89706-4a2f-45c7-a009-639d795049cf",
      "name": "尾長 晶乃",
      "shortName": "尾長 晶乃",
      "another": "翼成",
      "attribute": "electric",
      "imagePath": "akino_a"
   },
   {
      "id": "9819e913-2a7b-4a6b-a6c1-8241266f9c59",
      "name": "巽 竜子",
      "shortName": "巽 竜子",
      "attribute": "gravity",
      "imagePath": "ryuuko_n"
   },
   {
      "id": "405ac27a-01d0-40d7-a974-098664d10fac",
      "name": "鳳 加純",
      "shortName": "鳳 加純",
      "attribute": "heat",
      "imagePath": "kasumi_o_n"
   },
   {
      "id": "1002ddcb-e68d-473d-8758-a3f479e5440a",
      "name": "吾妻 京",
      "shortName": "吾妻 京",
      "attribute": "gravity",
      "imagePath": "kei_a_n"
   },
   {
      "id": "536f58d8-4bd0-4171-8c41-1d0f6e645c8d",
      "name": "アンジェリカ・グラズノワ",
      "shortName": "アンジェリカ・G",
      "attribute": "freeze",
      "imagePath": "angelica_n"
   },
   {
      "id": "3967a736-e74f-588b-ae57-ee4aa3f61db8",
      "name": "金潟 すぐみ",
      "shortName": "金潟 すぐみ",
      "attribute": "electric",
      "imagePath": "sugumi_n"
   },
   {
      "id": "f8aeb6e2-f463-4f7b-8184-b0905c98ebb4",
      "name": "金潟 すぐみ",
      "shortName": "金潟 すぐみ",
      "another": "臥薪",
      "attribute": "electric",
      "imagePath": "sugumi_a"
   },
   {
      "id": "54f55f5a-cbc4-5fd2-9ca1-1bae0f554b9d",
      "name": "新居目 安里",
      "shortName": "新居目 安里",
      "attribute": "gravity",
      "imagePath": "yasuri_n"
   },
   {
      "id": "2b9e1b53-d220-4f92-9b73-3e26aee501ab",
      "name": "新居目 安里",
      "shortName": "新居目 安里",
      "attribute": "gravity",
      "another": "紺碧",
      "imagePath": "yasuri_a"
   },
   {
      "id": "c9217bac-a5e1-482c-9e07-d40f8e2d280b",
      "name": "的場 アオイ",
      "shortName": "的場 アオイ",
      "attribute": "freeze",
      "imagePath": "aoi_n"
   },
   {
      "id": "ba247b94-990c-4028-94f1-a3ed1efc386a",
      "name": "的場 アオイ",
      "shortName": "的場 アオイ",
      "another": "冀望",
      "attribute": "freeze",
      "imagePath": "aoi_a"
   },
   {
      "id": "23df92f0-edc3-4feb-9246-3ccd546ab7c9",
      "name": "在賀 奈々",
      "shortName": "在賀 奈々",
      "attribute": "gravity",
      "imagePath": "nana_n"
   },
   {
      "id": "2a2ed6d7-0515-4e30-a08a-22f4f0984bb2",
      "name": "在賀 奈々",
      "shortName": "在賀 奈々",
      "another": "星詠",
      "attribute": "gravity",
      "imagePath": "nana_a"
   },
   {
      "id": "c1526023-6acb-46b3-8074-2db6e7384ad9",
      "name": "宮南 ひかり",
      "shortName": "宮南 ひかり",
      "attribute": "heat",
      "imagePath": "hikari_n"
   },
   {
      "id": "99bc6986-02cd-455d-ab35-efc9d33e7664",
      "name": "宮南 ひかり",
      "shortName": "宮南 ひかり",
      "attribute": "heat",
      "another": "爛漫",
      "imagePath": "hikari_a"
   },
   {
      "id": "d41a8ef7-8548-4fb3-98d2-3bcc74310931",
      "name": "我龍 絵美",
      "shortName": "我龍 絵美",
      "attribute": "gravity",
      "imagePath": "emi_n"
   },
   {
      "id": "c0e023eb-2869-490b-b06e-105e2d92061e",
      "name": "我龍 絵美",
      "shortName": "我龍 絵美",
      "another": "雅馴",
      "attribute": "gravity",
      "imagePath": "emi_a"
   },
   {
      "id": "a911990e-2f70-41c3-a4f9-86f747dfb476",
      "name": "天狐 天",
      "shortName": "天狐 天",
      "attribute": "freeze",
      "imagePath": "sora_n"
   },
   {
      "id": "e672563e-0730-4b33-a3f0-bc9719a5efb1",
      "name": "天狐 天",
      "shortName": "天狐 天",
      "attribute": "freeze",
      "another": "御侠",
      "imagePath": "sora_a"
   },
   {
      "id": "33b2a6d8-a827-4de3-877b-2404adbe144a",
      "name": "波佐見 利佳",
      "shortName": "波佐見 利佳",
      "attribute": "gravity",
      "imagePath": "rika_n"
   },
   {
      "id": "9d5e2e61-c0df-4b84-96a4-8f34ff8abe59",
      "name": "波佐見 利佳",
      "shortName": "波佐見 利佳",
      "attribute": "gravity",
      "another": "勇断",
      "imagePath": "rika_a"
   },
   {
      "id": "b4f7d50b-209d-4cd8-8d50-1c61a26bff4c",
      "name": "春日丘 もえ",
      "shortName": "春日丘 もえ",
      "attribute": "heat",
      "imagePath": "moe_n"
   },
   {
      "id": "c56f43b8-7361-4876-9ec8-32dfac7a3983",
      "name": "春日丘 もえ",
      "shortName": "春日丘 もえ",
      "attribute": "heat",
      "another": "萌芽",
      "imagePath": "moe_a"
   },
   {
      "id": "110ac47c-2dbe-443d-a807-46a4d95f7d26",
      "name": "アデライーデ・ブルートハウゼン",
      "shortName": "アデライーデ・B",
      "attribute": "freeze",
      "imagePath": "adi_n"
   },
   {
      "id": "3bebc340-b86c-4074-9399-53c633b48985",
      "name": "アデライーデ・ブルートハウゼン",
      "shortName": "アデライーデ・B",
      "attribute": "freeze",
      "another": "瑞花",
      "imagePath": "adi_a"
   },
   {
      "id": "ef366181-04c0-4143-9d8f-fbff5b5e3a06",
      "name": "ニコル・フランシスカ",
      "shortName": "ニコル・F",
      "attribute": "freeze",
      "imagePath": "nicole_n"
   },
   {
      "id": "6b2b6d41-587b-49e2-9d2e-8ed804cb91a7",
      "name": "ノエル・フランシスカ",
      "shortName": "ノエル・F",
      "attribute": "gravity",
      "imagePath": "noelle_n"
   },
   {
      "id": "f032ced7-b64d-4771-afb9-190732237a37",
      "name": "高幡 のどか",
      "shortName": "高幡 のどか",
      "attribute": "electric",
      "imagePath": "nodoka_n",
      "collaboration": true
   },
   {
      "id": "e4402580-cb5f-485c-870a-ef592db04a64",
      "name": "高幡 のどか",
      "shortName": "高幡 のどか",
      "another": "師門",
      "attribute": "heat",
      "imagePath": "nodoka_a",
      "collaboration": true
   },
   {
      "id": "962b89a8-1a52-5d7f-afc8-609b72f9299b",
      "name": "轟雷",
      "shortName": "轟雷",
      "attribute": "gravity",
      "collaboration": true,
      "imagePath": "gourai_n"
   },
   {
      "id": "477037d5-d301-52da-90c0-16b08aa79749",
      "name": "スティレット",
      "shortName": "スティレット",
      "attribute": "gravity",
      "collaboration": true,
      "imagePath": "stylet_n"
   },
   {
      "id": "2033f9d1-7a28-5cb5-804c-5a8c807df48c",
      "name": "バーゼラルド",
      "shortName": "バーゼラルド",
      "attribute": "electric",
      "collaboration": true,
      "imagePath": "baselard_n"
   },
   {
      "id": "c328f616-91c6-58a7-b2cc-f9610f337e79",
      "name": "フレズヴェルク",
      "shortName": "フレズヴェルク",
      "attribute": "gravity",
      "collaboration": true,
      "imagePath": "hresvelgr_n"
   },
   {
      "id": "c82403d5-dd04-4873-bcf3-fedd093a3937",
      "name": "源内 あお",
      "shortName": "源内 あお",
      "attribute": "heat",
      "collaboration": true,
      "imagePath": "ao_n"
   },
   {
      "id": "d33ecd8a-408f-4eb5-aadf-956a66c93523",
      "name": "寿 武希子",
      "shortName": "寿 武希子",
      "attribute": "freeze",
      "collaboration": true,
      "imagePath": "bukiko_n"
   },
   {
      "id": "a2998e8e-2663-55f7-8a45-6bfec605f73b",
      "name": "SOLラプター",
      "shortName": "SOLラプター",
      "attribute": "heat",
      "collaboration": true,
      "imagePath": "SOL_Raptor"
   },
   {
      "id": "322c123c-fabe-52d7-be0b-4d695b1a9904",
      "name": "SOLラプター",
      "shortName": "SOLラプター",
      "another": "[ストライク]",
      "attribute": "freeze",
      "collaboration": true,
      "imagePath": "SOL_Strike_Raptor"
   },
   {
      "id": "332933c5-577a-537e-a924-1af495a6a2f2",
      "name": "宮藤 芳佳",
      "shortName": "宮藤 芳佳",
      "attribute": "electric",
      "collaboration": true,
      "imagePath": "yosika_n"
   },
   {
      "id": "5df7f01c-96e6-43fd-b157-d89ccc333935",
      "name": "坂本 美緒",
      "shortName": "坂本 美緒",
      "attribute": "heat",
      "collaboration": true,
      "imagePath": "mio_n"
   },
   {
      "id": "7625822c-bdab-5d62-b625-7c721c503fed",
      "name": "リネット・ビショップ",
      "shortName": "リネット・B",
      "attribute": "gravity",
      "collaboration": true,
      "imagePath": "rinette_n"
   },
   {
      "id": "891e794c-e5f3-4589-95bf-a5a7ecdf3594",
      "name": "ペリーヌ＝H・クロステルマン",
      "shortName": "ペリーヌ・C",
      "attribute": "electric",
      "collaboration": true,
      "imagePath": "perrine_n"
   },
   {
      "id": "91806526-f37b-5cd0-88fe-429986c351c4",
      "name": "ゲルトルート・バルクホルン",
      "shortName": "ゲルトルート・B",
      "attribute": "heat",
      "collaboration": true,
      "imagePath": "gertrud_n"
   },
   {
      "id": "b71a5cb6-cc72-5068-9df2-1cf91bd6b8a8",
      "name": "エーリカ・ハルトマン",
      "shortName": "エーリカ・H",
      "attribute": "freeze",
      "collaboration": true,
      "imagePath": "erica_n"
   },
   {
      "id": "00b06bb8-0f85-45d8-84fd-a55bcc1c575b",
      "name": "フランチェスカ・ルッキーニ",
      "shortName": "フランチェスカ・L",
      "attribute": "electric",
      "collaboration": true,
      "imagePath": "francesca_n"
   },
   {
      "id": "2e54d23c-9357-40a6-a73d-96e1bd48e5a8",
      "name": "シャーロット・E・イェーガー",
      "shortName": "シャーロット・Y",
      "attribute": "heat",
      "collaboration": true,
      "imagePath": "Charlotte_n"
   },
   {
      "id": "9fae8702-794f-5eff-a274-a6350557dfb2",
      "name": "星月 みき",
      "shortName": "星月 みき",
      "attribute": "heat",
      "collaboration": true,
      "imagePath": "miki_n"
   },
   {
      "id": "a3a92e01-5092-4107-9515-5153a5b5099b",
      "name": "天野 望",
      "shortName": "天野 望",
      "attribute": "electric",
      "collaboration": true,
      "imagePath": "nozomi_n"
   },
   {
      "id": "65a96986-baad-5d88-9b6d-190849d69303",
      "name": "常磐 くるみ",
      "shortName": "常磐 くるみ",
      "attribute": "freeze",
      "collaboration": true,
      "imagePath": "kurumi_n"
   },
   {
      "id": "a77bdfad-c85d-4b3e-8825-0fc1efe81a2f",
      "name": "粒咲 あんこ",
      "shortName": "粒咲 あんこ",
      "attribute": "gravity",
      "collaboration": true,
      "imagePath": "anko_n"
   },
   {
      "id": "891695f4-d6cc-4563-aa61-18119c548b63",
      "name": "芹沢 蓮華",
      "shortName": "芹沢 蓮華",
      "attribute": "gravity",
      "collaboration": true,
      "imagePath": "renge_n"
   },
   {
      "id": "8412207f-fc04-4c7d-8d7a-6a2d8e8ecf49",
      "name": "楠 明日葉",
      "shortName": "楠 明日葉",
      "attribute": "freeze",
      "collaboration": true,
      "imagePath": "asuha_n"
   },
   {
      "id": "678e4d86-d797-5573-8ffd-cb89dfd4c32a",
      "name": "綿木 ミシェル",
      "shortName": "綿木 ミシェル",
      "attribute": "electric",
      "collaboration": true,
      "imagePath": "michel_n"
   },
   {
      "id": "267cc6ea-24aa-5d10-859c-d81e4a77929d",
      "name": "サドネ",
      "shortName": "サドネ",
      "attribute": "gravity",
      "collaboration": true,
      "imagePath": "sadone_n"
   },
   {
      "id": "55ad3d56-27f8-4411-a830-cc4699fbad19",
      "name": "煌上 花音",
      "shortName": "煌上 花音",
      "attribute": "electric",
      "collaboration": true,
      "imagePath": "kanon_n"
   },
   {
      "id": "4ca54aa9-b3f5-4ca3-ae07-2c730d5e9197",
      "name": "国枝 詩穂",
      "shortName": "国枝 詩穂",
      "attribute": "freeze",
      "collaboration": true,
      "imagePath": "shiho_n"
   },
   {
      "id": "de8e9e30-679b-45cf-b35b-101522574904",
      "name": "カスミ",
      "shortName": "カスミ",
      "attribute": "freeze",
      "collaboration": true,
      "imagePath": "kasumi_n"
   },
   {
      "id": "5954d6f1-c5e7-4421-99c0-4ad19daaf051",
      "name": "マリー・ローズ",
      "shortName": "マリー・ローズ",
      "attribute": "gravity",
      "collaboration": true,
      "imagePath": "marie_n"
   },
   {
      "id": "1cb4b6e9-d5e6-43ac-a89c-6ba048b23254",
      "name": "女天狗",
      "shortName": "女天狗",
      "attribute": "heat",
      "collaboration": true,
      "imagePath": "nyoteng_n"
   },
   {
      "id": "6fd2ee97-cabb-4a1a-ba8d-d0dfd805e5f1",
      "name": "シルフィーII",
      "shortName": "シルフィーII",
      "attribute": "electric",
      "collaboration": true,
      "imagePath": "sylphyII"
   },
   {
      "id": "5d1e451a-078b-4db0-b6f4-97d759e33c41",
      "name": "シルフィーII/Mode-B",
      "shortName": "シルフィーII/B",
      "attribute": "gravity",
      "collaboration": true,
      "imagePath": "sylphyII_B"
   },
   {
      "id": "0e143eae-9f05-4ace-9ef5-a4b1360db0a7",
      "name": "アヤ",
      "shortName": "アヤ",
      "attribute": "electric",
      "imagePath": "aya_n",
      "collaboration": true
   },
   {
      "id": "509a205f-b54e-4f92-b354-65bdb4bf7efc",
      "name": "ユキ",
      "shortName": "ユキ",
      "attribute": "freeze",
      "imagePath": "yuki_n",
      "collaboration": true
   },
   {
      "id": "acc32aae-3dff-496e-aeaa-1579a2b38dc4",
      "name": "ヤマダ",
      "shortName": "ヤマダ",
      "attribute": "gravity",
      "imagePath": "yamada_n",
      "collaboration": true
   },
   {
      "id": "054686c2-0ef7-4340-8b8f-17cc9894bb34",
      "name": "AIT Ti2",
      "shortName": "Ti2",
      "attribute": "heat",
      "imagePath": "ti2_n",
      "collaboration": true
   },
   {
      "id": "7bdd8398-1cc3-4e73-b83f-74c9e076737d",
      "name": "AIT 【イア・レトナ】",
      "shortName": "イア・レトナ",
      "another": "【イア・レトナ】",
      "attribute": "freeze",
      "collaboration": true,
      "imagePath": "ti2_a"
   },
   {
      "id": "069119a5-f553-42ff-9752-789580d5a24e",
      "name": "イブリー・ハッド",
      "shortName": "イブリー・ハッド",
      "attribute": "electric",
      "collaboration": true,
      "imagePath": "ivry_n"
   },
   {
      "id": "8401e18e-fb20-41c1-84ad-3a38ef7afb89",
      "name": "牧瀬紅 莉栖",
      "shortName": "牧瀬紅 莉栖",
      "attribute": "gravity",
      "collaboration": true,
      "imagePath": "makise_n"
   },
   {
      "id": "85f35c4b-f091-46f2-a168-a882815adad2",
      "name": "阿万音 鈴羽",
      "shortName": "阿万音 鈴羽",
      "attribute": "electric",
      "collaboration": true,
      "imagePath": "suzuha_n"
   },
   {
      "id": "0afbf81c-d16d-4149-9c76-6e2267270c4c",
      "name": "ターニャ・デグレチャフ",
      "shortName": "ターニャ",
      "attribute": "electric",
      "collaboration": true,
      "imagePath": "tanya_n"
   },
   {
      "id": "43dacae5-5f09-43bf-892f-4c25b37b66ee",
      "name": "ヴィクトーリヤ・イヴァーノヴナ・セレブリャコーフ",
      "shortName": "ヴィーシャ",
      "attribute": "heat",
      "collaboration": true,
      "imagePath": "viktoriya_n"
   },
   {
      "id": "b6c36e7b-83d6-43cb-baad-88d5967258c3",
      "name": "ケイ",
      "shortName": "ケイ",
      "attribute": "heat",
      "collaboration": true,
      "imagePath": "kei_n"
   },
   {
      "id": "73ccfc84-b0ab-454a-aee0-651858f70640",
      "name": "ユリ",
      "shortName": "ユリ",
      "attribute": "freeze",
      "collaboration": true,
      "imagePath": "yuri_n"
   },
   {
      "id": "5c89ef70-0305-4e2f-836d-7859680270c8",
      "name": "初音 ミク",
      "shortName": "初音 ミク",
      "attribute": "freeze",
      "collaboration": true,
      "imagePath": "miku_n"
   },
   {
      "id": "3c793b08-b1b4-4a25-b330-5ad4d2b36035",
      "name": "初音 ミク",
      "shortName": "初音 ミク",
      "attribute": "heat",
      "collaboration": true,
      "another": true,
      "imagePath": "miku_a"
   }
]
